AUTHORS
LICENSE
MANIFEST.in
NEWS
README.rst
setup.py
pymdstat/__init__.py
pymdstat/pymdstat.py
pymdstat.egg-info/PKG-INFO
pymdstat.egg-info/SOURCES.txt
pymdstat.egg-info/dependency_links.txt
pymdstat.egg-info/top_level.txt