Metadata-Version: 1.1
Name: pymdstat
Version: 0.4.2
Summary: Python library to parse Linux /proc/mdstat
Home-page: https://github.com/nicolargo/pymdstat
Author: Nicolas Hennion
Author-email: nicolas@nicolargo.com
License: MIT
Keywords: raid linux
Platform: UNKNOWN
Classifier: Development Status :: 4 - Beta
Classifier: Intended Audience :: Developers
Classifier: License :: OSI Approved :: MIT License
Classifier: Operating System :: POSIX :: Linux
Classifier: Programming Language :: Python :: 2
Classifier: Programming Language :: Python :: 3
Classifier: Topic :: Software Development :: Libraries :: Python Modules
